fano/__init__.py
fano/photons/__init__.py
fano/photons/areas/__init__.py
fano/photons/areas/_ionization.py
fano/photons/areas/_ionization_test.py
fano/photons/areas/epdl-silicon.endf
fano-0.0.0.dist-info/METADATA
fano-0.0.0.dist-info/WHEEL
fano-0.0.0.dist-info/top_level.txt
fano-0.0.0.dist-info/RECORD
