Metadata-Version: 2.1
Name: fano
Version: 0.0.0
Summary: A Python library for modeling the Fano factor and pair-creation energy of silicon
Author-email: "Roy T. Smart" <roytsmart@gmail.com>
Project-URL: Homepage, https://github.com/sun-data/fano
Project-URL: Documentation, https://optika.readthedocs.io
Classifier: Programming Language :: Python :: 3
Requires-Python: >=3.10
Requires-Dist: numpy
Requires-Dist: astropy
Requires-Dist: numba
Requires-Dist: endf
Provides-Extra: doc
Requires-Dist: pytest ; extra == 'doc'
Requires-Dist: matplotlib ; extra == 'doc'
Requires-Dist: graphviz ; extra == 'doc'
Requires-Dist: sphinx-autodoc-typehints ; extra == 'doc'
Requires-Dist: sphinxcontrib-bibtex ; extra == 'doc'
Requires-Dist: pydata-sphinx-theme ; extra == 'doc'
Requires-Dist: ipykernel ; extra == 'doc'
Requires-Dist: jupyter-sphinx ; extra == 'doc'
Requires-Dist: sphinx-favicon ; extra == 'doc'
Provides-Extra: test
Requires-Dist: pytest ; extra == 'test'
